{
    "AccountName": "TestAccount_NewSales_CO_Large",
    "AccountOrgNumber": "2000000008",
    "CSREmail": "abhinav.gupta@capgemini.com",
    "CSRName": "Abhinav Gupta",
    "CSRPhone": "+91 7838275004",
    "CommentsQuotation": "v",
    "ContactEmail": "arup.rishi@capgemini.com",
    "ContactName": "Arup Rishi Test",
    "CustomerNeedsBusiness": "1",
    "CustomerNeedsIT": "r",
    "CustomerNeedsMobileSubs": "w",
    "CustomerNeedsSwitch": "e",
    "QuoteCreatedDate": "2023-06-27",
    "QuoteNumber": "00011680",
    "SolutionBusiness": "d",
    "SolutionIT": "hv",
    "SolutionMobileSubs": "f",
    "SolutionSwitch": "gh",
    "Status": "Signed",
    "isRAcustomer": true,
    "result": {
        "COItems": null,
        "GroupExist": true,
        "Line": [
        ],
        "MAA": 0,
        "MAF": 0,
        "RTCUser": 0,
        "ST": [
            {
                "City": "SOLNA",
                "StreetAd": "TESTDA",
                "StreetName": "1SB"
            }
        ],
        "TBPlusBindingPeriod": "",
        "TBProBindingPeriod": "",
        "TBSBindingPeriod": "",
        "TCSDBindingPeriod": "",
        "TCWIBindingPeriod": "",
        "TDNBindingPeriod": "",
        "TotalDeductedOTF": 0,
        "TotalEUSOTC": 0,
        "TotalEUSRTC": 0,
        "TotalGRPDeductedCOOTF": 0,
        "TotalGRPOTC": 1,
        "TotalGRPRTC": 6052,
        "TotalHERAOTC": 0,
        "TotalHERARTC": 0,
        "TotalHWOTC": 0,
        "TotalHWRTC": 0,
        "TotalInsOTC": 0,
        "TotalInsRTC": 0,
        "TotalJobbMobilOTC": 0,
        "TotalJobbMobilRTC": 0,
        "TotalMBBOTC": 0,
        "TotalMBBRTC": 0,
        "TotalOTC": 0,
        "TotalOffice365OTCB0": 0,
        "TotalOffice365OTCB12": 0,
        "TotalOffice365OTCB36": 0,
        "TotalOffice365RTCB0": 0,
        "TotalOffice365RTCB12": 0,
        "TotalOffice365RTCB36": 0,
        "TotalPersonalOTC": 0,
        "TotalPersonalRTC": 0,
        "TotalRTC": 0,
        "TotalRTCCompany": 0,
        "TotalRTCSum": 0,
        "TotalRTCSum3": 0,
        "TotalRTCSumITDaaS": 0,
        "TotalRTCUser": 0,
        "TotalSmartConnectOTC": 0,
        "TotalSmartConnectRTC": 0,
        "TotalSmartSecOTC": 0,
        "TotalSmartSecRTC": 0,
        "TotalTBPL1OTC": 0,
        "TotalTBPL1RTC": 0,
        "TotalTBPR1OTC": 0,
        "TotalTBPR1RTC": 0,
        "TotalTBS1OTC": 0,
        "TotalTBS1RTC": 0,
        "TotalTCSD1OTC": 0,
        "TotalTCSD1RTC": 0,
        "TotalTCWI1OTC": 0,
        "TotalTCWI1RTC": 0,
        "TotalTDN1OTC": 0,
        "TotalTDN1RTC": 0,
        "TotalTouchPointOTC": 0,
        "TotalTouchPointPlusOTC": 0,
        "TotalTouchPointPlusRTC": 0,
        "TotalTouchPointRTC": 0,
        "group1": [
            {
                "COItems": [
                    {
                        "ChildItem": [
                        ],
                        "EnglishName": "Bredband Pro 100 Mbit/s",
                        "GroupExist": true,
                        "GroupUnqIdent": "Group 1",
                        "HeraType": "",
                        "HeraTypeSWE": "",
                        "OTC": "SEK0,00",
                        "ProductCode": "CO-BBPRO-100MB",
                        "Qn": 1,
                        "RTC": "SEK1 789,00",
                        "StreetAd": "",
                        "StreetName": "",
                        "SwedishName": "Bredband Pro 100 Mbit/s",
                        "isHERA": false,
                        "isSub": true,
                        "isTBPL": false,
                        "isTBPR": true,
                        "isTBS": false,
                        "isTCSD": false,
                        "isTCWI": false,
                        "isTDN": false
                    },
                    {
                        "ChildItem": [
                        ],
                        "EnglishName": "Bredband Pro 100 Mbit/s",
                        "GroupExist": true,
                        "GroupUnqIdent": "Group 1",
                        "HeraType": "",
                        "HeraTypeSWE": "",
                        "OTC": "SEK1,00",
                        "ProductCode": "CO-BBPRO-100MB",
                        "Qn": 1,
                        "RTC": "SEK1,00",
                        "StreetAd": "",
                        "StreetName": "",
                        "SwedishName": "Bredband Pro 100 Mbit/s",
                        "isHERA": false,
                        "isSub": true,
                        "isTBPL": false,
                        "isTBPR": true,
                        "isTBS": false,
                        "isTCSD": false,
                        "isTCWI": false,
                        "isTDN": false
                    },
                    {
                        "ChildItem": [
                        ],
                        "EnglishName": "Bredband Pro 100 Mbit/s",
                        "GroupExist": true,
                        "GroupUnqIdent": "Group 1",
                        "HeraType": "",
                        "HeraTypeSWE": "",
                        "OTC": "SEK0,00",
                        "ProductCode": "CO-BBPRO-100MB",
                        "Qn": 1,
                        "RTC": "SEK2 262,00",
                        "StreetAd": "",
                        "StreetName": "",
                        "SwedishName": "Bredband Pro 100 Mbit/s",
                        "isHERA": false,
                        "isSub": true,
                        "isTBPL": false,
                        "isTBPR": true,
                        "isTBS": false,
                        "isTCSD": false,
                        "isTCWI": false,
                        "isTDN": false
                    },
                    {
                        "ChildItem": [
                        ],
                        "EnglishName": "Bredband Pro 100 Mbit/s",
                        "GroupExist": true,
                        "GroupUnqIdent": "Group 1",
                        "HeraType": "",
                        "HeraTypeSWE": "",
                        "OTC": "SEK0,00",
                        "ProductCode": "CO-BBPRO-100MB",
                        "Qn": 1,
                        "RTC": "SEK0,00",
                        "StreetAd": "",
                        "StreetName": "",
                        "SwedishName": "Bredband Pro 100 Mbit/s",
                        "isHERA": false,
                        "isSub": true,
                        "isTBPL": false,
                        "isTBPR": true,
                        "isTBS": false,
                        "isTCSD": false,
                        "isTCWI": false,
                        "isTDN": false
                    }
                ],
                "GroupName": "G2",
                "SP": [
                    {
                        "City": "STACKU",
                        "StreetAd": "4",
                        "StreetName": "9"
                    }
                ],
                "TBPlusBindingPeriod": "",
                "TBProBindingPeriod": "36",
                "TBSBindingPeriod": "",
                "TCSDBindingPeriod": "",
                "TCWIBindingPeriod": "",
                "TDNBindingPeriod": "",
                "TotalGRPALLOTC": 0,
                "TotalGRPALLRTC": 1789,
                "TotalHERAOTC": 0,
                "TotalHERARTC": 0,
                "TotalTBPLOTC": 0,
                "TotalTBPLRTC": 0,
                "TotalTBPROTC": 0,
                "TotalTBPRRTC": 1789,
                "TotalTBSOTC": 0,
                "TotalTBSRTC": 0,
                "TotalTCSDOTC": 0,
                "TotalTCSDRTC": 0,
                "TotalTCWIOTC": 0,
                "TotalTCWIRTC": 0,
                "TotalTDNOTC": 0,
                "TotalTDNRTC": 0,
                "groupIndex": 1,
                "isHERA1": false,
                "istbplusG": false,
                "istbproG": true,
                "istbstartG": false,
                "istcsdG": false,
                "istcwlG": false,
                "istdnG": false
            },
            {
                "COItems": [
                    {
                        "ChildItem": [
                        ],
                        "EnglishName": null,
                        "GroupExist": true,
                        "GroupUnqIdent": "Group 2",
                        "HeraType": "Secondary Access",
                        "HeraTypeSWE": "Sekundär access",
                        "OTC": "SEK0,00",
                        "ProductCode": "CO-HERA-ALL",
                        "Qn": 1,
                        "RTC": "SEK1 789,00",
                        "StreetAd": "3",
                        "StreetName": "12",
                        "SwedishName": "HERA XYZ",
                        "isHERA": true,
                        "isSub": true,
                        "isTBPL": false,
                        "isTBPR": false,
                        "isTBS": false,
                        "isTCSD": false,
                        "isTCWI": false,
                        "isTDN": false
                    },
                    {
                        "ChildItem": [
                        ],
                        "EnglishName": "Bredband Pro 200 Mbit/s",
                        "GroupExist": true,
                        "GroupUnqIdent": "Group 2",
                        "HeraType": "",
                        "HeraTypeSWE": "",
                        "OTC": "SEK0,00",
                        "ProductCode": "CO-BBPRO-200MB",
                        "Qn": 1,
                        "RTC": "SEK1 789,00",
                        "StreetAd": "",
                        "StreetName": "",
                        "SwedishName": "Bredband Pro 200 Mbit/s",
                        "isHERA": false,
                        "isSub": true,
                        "isTBPL": false,
                        "isTBPR": true,
                        "isTBS": false,
                        "isTCSD": false,
                        "isTCWI": false,
                        "isTDN": false
                    },
                    {
                        "ChildItem": [
                        ],
                        "EnglishName": null,
                        "GroupExist": true,
                        "GroupUnqIdent": "Group 2",
                        "HeraType": "Secondary Access",
                        "HeraTypeSWE": "Sekundär access",
                        "OTC": "SEK1,00",
                        "ProductCode": "CO-HERA-ALL",
                        "Qn": 1,
                        "RTC": "SEK1,00",
                        "StreetAd": "3",
                        "StreetName": "12",
                        "SwedishName": "HERA XYZ",
                        "isHERA": true,
                        "isSub": true,
                        "isTBPL": false,
                        "isTBPR": false,
                        "isTBS": false,
                        "isTCSD": false,
                        "isTCWI": false,
                        "isTDN": false
                    },
                    {
                        "ChildItem": [
                        ],
                        "EnglishName": "Bredband Pro 200 Mbit/s",
                        "GroupExist": true,
                        "GroupUnqIdent": "Group 2",
                        "HeraType": "",
                        "HeraTypeSWE": "",
                        "OTC": "SEK1,00",
                        "ProductCode": "CO-BBPRO-200MB",
                        "Qn": 1,
                        "RTC": "SEK1,00",
                        "StreetAd": "",
                        "StreetName": "",
                        "SwedishName": "Bredband Pro 200 Mbit/s",
                        "isHERA": false,
                        "isSub": true,
                        "isTBPL": false,
                        "isTBPR": true,
                        "isTBS": false,
                        "isTCSD": false,
                        "isTCWI": false,
                        "isTDN": false
                    },
                    {
                        "ChildItem": [
                        ],
                        "EnglishName": null,
                        "GroupExist": true,
                        "GroupUnqIdent": "Group 2",
                        "HeraType": "Secondary Access",
                        "HeraTypeSWE": "Sekundär access",
                        "OTC": "SEK0,00",
                        "ProductCode": "CO-HERA-ALL",
                        "Qn": 1,
                        "RTC": "SEK2 262,00",
                        "StreetAd": "3",
                        "StreetName": "12",
                        "SwedishName": "HERA XYZ",
                        "isHERA": true,
                        "isSub": true,
                        "isTBPL": false,
                        "isTBPR": false,
                        "isTBS": false,
                        "isTCSD": false,
                        "isTCWI": false,
                        "isTDN": false
                    },
                    {
                        "ChildItem": [
                        ],
                        "EnglishName": "Bredband Pro 200 Mbit/s",
                        "GroupExist": true,
                        "GroupUnqIdent": "Group 2",
                        "HeraType": "",
                        "HeraTypeSWE": "",
                        "OTC": "SEK0,00",
                        "ProductCode": "CO-BBPRO-200MB",
                        "Qn": 1,
                        "RTC": "SEK2 262,00",
                        "StreetAd": "",
                        "StreetName": "",
                        "SwedishName": "Bredband Pro 200 Mbit/s",
                        "isHERA": false,
                        "isSub": true,
                        "isTBPL": false,
                        "isTBPR": true,
                        "isTBS": false,
                        "isTCSD": false,
                        "isTCWI": false,
                        "isTDN": false
                    },
                    {
                        "ChildItem": [
                        ],
                        "EnglishName": null,
                        "GroupExist": true,
                        "GroupUnqIdent": "Group 2",
                        "HeraType": "Secondary Access",
                        "HeraTypeSWE": "Sekundär access",
                        "OTC": "SEK0,00",
                        "ProductCode": "CO-HERA-ALL",
                        "Qn": 1,
                        "RTC": "SEK0,00",
                        "StreetAd": "3",
                        "StreetName": "12",
                        "SwedishName": "HERA XYZ",
                        "isHERA": true,
                        "isSub": true,
                        "isTBPL": false,
                        "isTBPR": false,
                        "isTBS": false,
                        "isTCSD": false,
                        "isTCWI": false,
                        "isTDN": false
                    },
                    {
                        "ChildItem": [
                        ],
                        "EnglishName": "Bredband Pro 200 Mbit/s",
                        "GroupExist": true,
                        "GroupUnqIdent": "Group 2",
                        "HeraType": "",
                        "HeraTypeSWE": "",
                        "OTC": "SEK0,00",
                        "ProductCode": "CO-BBPRO-200MB",
                        "Qn": 1,
                        "RTC": "SEK0,00",
                        "StreetAd": "",
                        "StreetName": "",
                        "SwedishName": "Bredband Pro 200 Mbit/s",
                        "isHERA": false,
                        "isSub": true,
                        "isTBPL": false,
                        "isTBPR": true,
                        "isTBS": false,
                        "isTCSD": false,
                        "isTCWI": false,
                        "isTDN": false
                    }
                ],
                "GroupName": "GR3",
                "SP": [
                    {
                        "City": "STOCKHOLM",
                        "StreetAd": "3",
                        "StreetName": "12"
                    }
                ],
                "TBPlusBindingPeriod": "",
                "TBProBindingPeriod": "36",
                "TBSBindingPeriod": "",
                "TCSDBindingPeriod": "",
                "TCWIBindingPeriod": "",
                "TDNBindingPeriod": "",
                "TotalGRPALLOTC": 1,
                "TotalGRPALLRTC": 2263,
                "TotalHERAOTC": 1,
                "TotalHERARTC": 1,
                "TotalTBPLOTC": 0,
                "TotalTBPLRTC": 0,
                "TotalTBPROTC": 0,
                "TotalTBPRRTC": 2262,
                "TotalTBSOTC": 0,
                "TotalTBSRTC": 0,
                "TotalTCSDOTC": 0,
                "TotalTCSDRTC": 0,
                "TotalTCWIOTC": 0,
                "TotalTCWIRTC": 0,
                "TotalTDNOTC": 0,
                "TotalTDNRTC": 0,
                "groupIndex": 2,
                "isHERA1": true,
                "istbplusG": false,
                "istbproG": true,
                "istbstartG": false,
                "istcsdG": false,
                "istcwlG": false,
                "istdnG": false
            },
            {
                "COItems": [
                    {
                        "ChildItem": [
                            {
                                "EnglishName": "Bredband Pro SLA C4",
                                "ExcludeItem": false,
                                "OTC": 0,
                                "OneTimeTotal": null,
                                "Qn": 1,
                                "RTC": 2000,
                                "RTCSum": null,
                                "SwedishName": "Bredband Pro SLA C4",
                                "Tmpflg": false,
                                "isDefaultTable": null,
                                "isITDaaSAddons": false,
                                "isITDaaSAddonsZero": false,
                                "isITDaaSCmpnyZero": false,
                                "isITDaaSCompany": false,
                                "isITDaaSUsers": false,
                                "isITDaaSUsersZero": false,
                                "isZeroTable": null
                            }
                        ],
                        "EnglishName": "Add-on Enhanced SLA",
                        "GroupExist": true,
                        "GroupUnqIdent": "Group 3",
                        "HeraType": "",
                        "HeraTypeSWE": "",
                        "OTC": "SEK0,00",
                        "ProductCode": "CO-BBPRO-SLA-TILLVAL",
                        "Qn": 1,
                        "RTC": "SEK1 789,00",
                        "StreetAd": "",
                        "StreetName": "",
                        "SwedishName": "Tillval Utökad SLA",
                        "isHERA": false,
                        "isSub": false,
                        "isTBPL": false,
                        "isTBPR": true,
                        "isTBS": false,
                        "isTCSD": false,
                        "isTCWI": false,
                        "isTDN": false
                    },
                    {
                        "ChildItem": [
                            {
                                "EnglishName": "Bredband Pro SLA C4",
                                "ExcludeItem": false,
                                "OTC": 0,
                                "OneTimeTotal": null,
                                "Qn": 1,
                                "RTC": 2000,
                                "RTCSum": null,
                                "SwedishName": "Bredband Pro SLA C4",
                                "Tmpflg": false,
                                "isDefaultTable": null,
                                "isITDaaSAddons": false,
                                "isITDaaSAddonsZero": false,
                                "isITDaaSCmpnyZero": false,
                                "isITDaaSCompany": false,
                                "isITDaaSUsers": false,
                                "isITDaaSUsersZero": false,
                                "isZeroTable": null
                            }
                        ],
                        "EnglishName": "Add-on Enhanced SLA",
                        "GroupExist": true,
                        "GroupUnqIdent": "Group 3",
                        "HeraType": "",
                        "HeraTypeSWE": "",
                        "OTC": "SEK1,00",
                        "ProductCode": "CO-BBPRO-SLA-TILLVAL",
                        "Qn": 1,
                        "RTC": "SEK1,00",
                        "StreetAd": "",
                        "StreetName": "",
                        "SwedishName": "Tillval Utökad SLA",
                        "isHERA": false,
                        "isSub": false,
                        "isTBPL": false,
                        "isTBPR": true,
                        "isTBS": false,
                        "isTCSD": false,
                        "isTCWI": false,
                        "isTDN": false
                    },
                    {
                        "ChildItem": [
                            {
                                "EnglishName": "Bredband Pro SLA C4",
                                "ExcludeItem": false,
                                "OTC": 0,
                                "OneTimeTotal": null,
                                "Qn": 1,
                                "RTC": 2000,
                                "RTCSum": null,
                                "SwedishName": "Bredband Pro SLA C4",
                                "Tmpflg": false,
                                "isDefaultTable": null,
                                "isITDaaSAddons": false,
                                "isITDaaSAddonsZero": false,
                                "isITDaaSCmpnyZero": false,
                                "isITDaaSCompany": false,
                                "isITDaaSUsers": false,
                                "isITDaaSUsersZero": false,
                                "isZeroTable": null
                            }
                        ],
                        "EnglishName": "Add-on Enhanced SLA",
                        "GroupExist": true,
                        "GroupUnqIdent": "Group 3",
                        "HeraType": "",
                        "HeraTypeSWE": "",
                        "OTC": "SEK0,00",
                        "ProductCode": "CO-BBPRO-SLA-TILLVAL",
                        "Qn": 1,
                        "RTC": "SEK2 262,00",
                        "StreetAd": "",
                        "StreetName": "",
                        "SwedishName": "Tillval Utökad SLA",
                        "isHERA": false,
                        "isSub": false,
                        "isTBPL": false,
                        "isTBPR": true,
                        "isTBS": false,
                        "isTCSD": false,
                        "isTCWI": false,
                        "isTDN": false
                    },
                    {
                        "ChildItem": [
                            {
                                "EnglishName": "Bredband Pro SLA C4",
                                "ExcludeItem": false,
                                "OTC": 0,
                                "OneTimeTotal": null,
                                "Qn": 1,
                                "RTC": 2000,
                                "RTCSum": null,
                                "SwedishName": "Bredband Pro SLA C4",
                                "Tmpflg": false,
                                "isDefaultTable": null,
                                "isITDaaSAddons": false,
                                "isITDaaSAddonsZero": false,
                                "isITDaaSCmpnyZero": false,
                                "isITDaaSCompany": false,
                                "isITDaaSUsers": false,
                                "isITDaaSUsersZero": false,
                                "isZeroTable": null
                            }
                        ],
                        "EnglishName": "Add-on Enhanced SLA",
                        "GroupExist": true,
                        "GroupUnqIdent": "Group 3",
                        "HeraType": "",
                        "HeraTypeSWE": "",
                        "OTC": "SEK0,00",
                        "ProductCode": "CO-BBPRO-SLA-TILLVAL",
                        "Qn": 1,
                        "RTC": "SEK0,00",
                        "StreetAd": "",
                        "StreetName": "",
                        "SwedishName": "Tillval Utökad SLA",
                        "isHERA": false,
                        "isSub": false,
                        "isTBPL": false,
                        "isTBPR": true,
                        "isTBS": false,
                        "isTCSD": false,
                        "isTCWI": false,
                        "isTDN": false
                    }
                ],
                "GroupName": "G8",
                "SP": [
                    {
                        "City": "SOLNA",
                        "StreetAd": "2",
                        "StreetName": "10"
                    },
                    {
                        "City": "STOCKHOLMNOIDA",
                        "StreetAd": "5",
                        "StreetName": "13"
                    }
                ],
                "TBPlusBindingPeriod": "",
                "TBProBindingPeriod": "36",
                "TBSBindingPeriod": "",
                "TCSDBindingPeriod": "",
                "TCWIBindingPeriod": "",
                "TDNBindingPeriod": "",
                "TotalGRPALLOTC": 0,
                "TotalGRPALLRTC": 2000,
                "TotalHERAOTC": 0,
                "TotalHERARTC": 0,
                "TotalTBPLOTC": 0,
                "TotalTBPLRTC": 0,
                "TotalTBPROTC": 0,
                "TotalTBPRRTC": 2000,
                "TotalTBSOTC": 0,
                "TotalTBSRTC": 0,
                "TotalTCSDOTC": 0,
                "TotalTCSDRTC": 0,
                "TotalTCWIOTC": 0,
                "TotalTCWIRTC": 0,
                "TotalTDNOTC": 0,
                "TotalTDNRTC": 0,
                "groupIndex": 3,
                "isHERA1": false,
                "istbplusG": false,
                "istbproG": true,
                "istbstartG": false,
                "istcsdG": false,
                "istcwlG": false,
                "istdnG": false
            }
        ],
        "groupedSites": [
            "a6K3H000000A2rTUAS",
            "a6K3H000000A2rRUAS",
            "a6K3H000000A2rSUAS",
            "a6K3H000000CrM4UAK"
        ],
        "is365": false,
        "is3651": false,
        "is3651B0": false,
        "is3651B12": false,
        "is3651B36": false,
        "is3651Zero": false,
        "is3651ZeroB0": false,
        "is3651ZeroB12": false,
        "is3651ZeroB36": false,
        "isALLINClusterAddons": null,
        "isAdditionalSites": true,
        "isAnvandarpaket": false,
        "isB2B": false,
        "isDefaultTable": false,
        "isEUS": false,
        "isEUS1": false,
        "isEUS1Zero": false,
        "isFT1Zero": false,
        "isHW": false,
        "isHWZero": false,
        "isITDaaS": false,
        "isITDaaS1": false,
        "isITDaaS2": false,
        "isITDaaSAddonsZero": false,
        "isITDaaSCmpny": false,
        "isITDaaSCmpnyZero": false,
        "isITDaaSStart": false,
        "isITDaaSStartZero": false,
        "isITDaaSStartincart": false,
        "isITDaaSUsers": false,
        "isITDaaSUsersZero": false,
        "isITDaaSZero": false,
        "isITDaaSincart": false,
        "isITDaaSincart1": false,
        "isITDaaSincart2": false,
        "isITDaaSincart3": false,
        "isJM": false,
        "isJobMobile": false,
        "isJobMobile1": false,
        "isJobMobile1Zero": false,
        "isMobile": false,
        "isMobile1": false,
        "isMobile1Zero": false,
        "isNT": true,
        "isOnlyHERA": false,
        "isPT": false,
        "isPT1": false,
        "isPT1Zero": false,
        "isReNeg": false,
        "isSC": false,
        "isSS": false,
        "isSS1": false,
        "isSS1Zero": false,
        "isSmartConnectV3": false,
        "isSmartConnectV31Zero": false,
        "isTBPL": true,
        "isTBPL1": false,
        "isTBPLZero": false,
        "isTBPR": true,
        "isTBPR1": false,
        "isTBPRZero": false,
        "isTBS": false,
        "isTBS1": false,
        "isTBSZero": false,
        "isTCSD": true,
        "isTCSD1": false,
        "isTCSDZero": false,
        "isTCWI": false,
        "isTCWI1": false,
        "isTCWIZero": false,
        "isTDN": true,
        "isTDN1": false,
        "isTDNZero": false,
        "isTF": false,
        "isTF1": false,
        "isTP": false,
        "isTP1": false,
        "isTP1Zero": false,
        "isTPP": false,
        "isTPP1": false,
        "isTPP1Zero": false,
        "isTotalClusterAddons": null,
        "isZeroTable": false,
        "isnonITDaaSTable": false
    }
}